n8n_workflow_builder/__init__.py
n8n_workflow_builder/cli.py
n8n_workflow_builder/models/__init__.py
n8n_workflow_builder/models/config.py
n8n_workflow_builder/services/__init__.py
n8n_workflow_builder/services/builder.py
n8n_workflow_builder/services/comparator.py
n8n_workflow_builder/services/n8n_client.py
n8n_workflow_builder/services/secrets.py
n8n_workflow_builder/templates/__init__.py
n8n_workflow_builder/utils/__init__.py
n8n_workflow_builder/utils/validation.py
n8n_workflow_builder-0.2.0.dist-info/licenses/LICENSE
n8n_workflow_builder-0.2.0.dist-info/METADATA
n8n_workflow_builder-0.2.0.dist-info/WHEEL
n8n_workflow_builder-0.2.0.dist-info/entry_points.txt
n8n_workflow_builder-0.2.0.dist-info/top_level.txt
n8n_workflow_builder-0.2.0.dist-info/RECORD
