Metadata-Version: 2.4
Name: n8n-workflow-builder
Version: 0.2.0
Summary: A Python library for building, managing, and deploying n8n workflows with configuration-driven templates
Author-email: Matt Ferrante <matt@heyferrante.com>
License: MIT
Project-URL: Homepage, https://github.com/ferrants/n8n-workflow-builder
Project-URL: Repository, https://github.com/ferrants/n8n-workflow-builder
Project-URL: Issues, https://github.com/ferrants/n8n-workflow-builder/issues
Project-URL: Documentation, https://github.com/ferrants/n8n-workflow-builder#readme
Keywords: n8n,workflow,automation,template,deployment
Classifier: Development Status :: 3 - Alpha
Classifier: Intended Audience :: Developers
Classifier: License :: OSI Approved :: MIT License
Classifier: Programming Language :: Python :: 3
Classifier: Programming Language :: Python :: 3.8
Classifier: Programming Language :: Python :: 3.9
Classifier: Programming Language :: Python :: 3.10
Classifier: Programming Language :: Python :: 3.11
Requires-Python: >=3.8
License-File: LICENSE
Requires-Dist: click>=8.0.0
Requires-Dist: pyyaml>=6.0
Requires-Dist: python-dotenv>=1.0.0
Requires-Dist: requests>=2.28.0
Requires-Dist: jinja2>=3.1.0
Requires-Dist: jsonschema>=4.0.0
Provides-Extra: dev
Requires-Dist: pytest>=7.0.0; extra == "dev"
Requires-Dist: pytest-cov>=4.0.0; extra == "dev"
Requires-Dist: black>=22.0.0; extra == "dev"
Requires-Dist: flake8>=5.0.0; extra == "dev"
Requires-Dist: mypy>=1.0.0; extra == "dev"
Dynamic: license-file
